TDebugger/TDebugger.py
TDebugger/config.yaml
TDebugger/TestAlgos/sorting.py
TDebugger/TestAlgos/test.py
TDebugger/fonts/OpenSans-Bold.ttf
TDebugger/fonts/OpenSans-Regular.ttf
TDebugger/fonts/Roboto-Bold.ttf
TDebugger/fonts/Roboto-Regular.ttf
TDebugger/themes/themes.yaml
TDebugger-0.2.3.1.dist-info/LICENSE.md
TDebugger-0.2.3.1.dist-info/METADATA
TDebugger-0.2.3.1.dist-info/WHEEL
TDebugger-0.2.3.1.dist-info/entry_points.txt
TDebugger-0.2.3.1.dist-info/top_level.txt
TDebugger-0.2.3.1.dist-info/RECORD
