Metadata-Version: 2.1
Name: TDebugger
Version: 0.2.3.1
Summary: A advanced python debugger with live tracing that outputs video logs of a program's execution.
Home-page: https://github.com/CCExtractor/TDebugger
Author: Jayesh Nirve
Author-email: nitinnirve@gmail.com
License: GPL-2.0
Platform: UNKNOWN
Classifier: Programming Language :: Python :: 3
Classifier: Programming Language :: Python :: 3.7
Requires-Dist: Pillow
Requires-Dist: opencv-python
Requires-Dist: numpy
Requires-Dist: pyyaml
